{
    "dns": {
        "servers": [
            "https+local://dns.google/dns-query"
        ]
    },
    "inbounds": [
        {
            "port": 80,
            "listen": "0.0.0.0",
            "protocol": "vmess",
            "settings": {
                "clients": [
                    {
                        "id": "11c4bcb9-36cf-4ade-8385-d42605cba2b5",
                        "alterId": 0
                    }
                ]
            },
            "streamSettings": {
                "network": "ws",
                "wsSettings": {
                    "path": "/en-us/img"
                }
            }
        },
        {
            "port": 25,
            "listen": "0.0.0.0",
            "protocol": "vmess",
            "settings": {
                "clients": [
                    {
                        "id": "11c4bcb9-36cf-4ade-8385-d42605cba2b5",
                        "alterId": 0
                    }
                ]
            }            
        },
        {
            "port": 27015,
            "listen": "0.0.0.0",
            "protocol": "vmess",
            "settings": {
                "clients": [
                    {
                        "id": "11c4bcb9-36cf-4ade-8385-d42605cba2b5",
                        "alterId": 0
                    }
                ]
            },
            "streamSettings": {
                "network": "mkcp",
                "kcpSettings": {
                    "uplinkCapacity": 90,
                    "downlinkCapacity": 90,
                    "congestion": false,
                    "header": {
                        "type": "srtp"
                    }
                }
            }
        }
    ],
    "outbounds": [
        {
            "protocol": "freedom",
            "settings": {
                "domainStrategy": "UseIPv4"
            }
        }
    ]
}
